devion/__init__.py
devion/main.py
devion/interfaces/__init__.py
devion/interfaces/cli_bridge.py
devion/interfaces/module_interface.py
devion/modules/__init__.py
devion/modules/analyze_module.py
devion/modules/config_module.py
devion/modules/deploy_module.py
devion/modules/fix_module.py
devion/modules/help_module.py
devion/modules/init_module.py
devion/modules/scan_module.py
devion/modules/setup_module.py
devion/modules/status_module.py
devion/modules/use_module.py
devion-0.1.20.dist-info/licenses/LICENSE
devion-0.1.20.dist-info/METADATA
devion-0.1.20.dist-info/WHEEL
devion-0.1.20.dist-info/top_level.txt
devion-0.1.20.dist-info/RECORD
