Metadata-Version: 2.4
Name: devion
Version: 0.1.20
Summary: Devion — Development Environment Manager (core python package)
Home-page: https://github.com/MattHeeper/Devion
Author: MattHeeper
License: Apache-2.0
Classifier: Programming Language :: Python :: 3
Classifier: License :: OSI Approved :: Apache Software License
Classifier: Operating System :: OS Independent
Requires-Python: >=3.11
License-File: LICENSE
Dynamic: author
Dynamic: classifier
Dynamic: description
Dynamic: description-content-type
Dynamic: home-page
Dynamic: license
Dynamic: license-file
Dynamic: requires-python
Dynamic: summary
